matrix_neighbors/__init__.py
matrix_neighbors-0.1.dist-info/LICENSE
matrix_neighbors-0.1.dist-info/METADATA
matrix_neighbors-0.1.dist-info/WHEEL
matrix_neighbors-0.1.dist-info/top_level.txt
matrix_neighbors-0.1.dist-info/RECORD
